{
    "prepare_queue": {
        "installed": [],
        "uninstalled": []
    },
    "config_munge": {
        "framework": {
            "AudioToolbox.framework": {
                "true": 1
            },
            "CoreBluetooth.framework": {
                "true": 1
            }
        },
        "config.xml": {
            "/*": {
                "<feature name=\"Notification\"><param name=\"ios-package\" value=\"CDVNotification\" /></feature>": 1,
                "<feature name=\"BCBluetooth\"><param name=\"ios-package\" value=\"BCBluetooth\" /></feature>": 1
            }
        }
    },
    "installed_plugins": {
        "org.apache.cordova.dialogs": {
            "PACKAGE_NAME": "com.jumacc.bcfindme"
        },
        "org.bcsphere.bluetooth": {
            "PACKAGE_NAME": "com.jumacc.bcfindme"
        }
    },
    "dependent_plugins": {}
}